rag_startups/__init__.py
rag_startups/__main__.py
rag_startups/cli.py
rag_startups/cli_models.py
rag_startups/embed_master.py
rag_startups/main.py
rag_startups/analysis/external_data.py
rag_startups/analysis/market_analyzer.py
rag_startups/analysis/market_size.py
rag_startups/config/__init__.py
rag_startups/config/config.py
rag_startups/config/migration.py
rag_startups/config/settings.py
rag_startups/config/validator.py
rag_startups/core/__init__.py
rag_startups/core/model_manager.py
rag_startups/core/model_migrations.py
rag_startups/core/model_service.py
rag_startups/core/rag_chain.py
rag_startups/core/rag_service.py
rag_startups/core/startup_metadata.py
rag_startups/data/__init__.py
rag_startups/data/convert_yc_data.py
rag_startups/data/loader.py
rag_startups/embeddings/__init__.py
rag_startups/embeddings/embedding.py
rag_startups/idea_generator/__init__.py
rag_startups/idea_generator/generator.py
rag_startups/idea_generator/processors.py
rag_startups/idea_generator/prompts.py
rag_startups/idea_generator/examples/basic_usage.py
rag_startups/utils/__init__.py
rag_startups/utils/caching.py
rag_startups/utils/exceptions.py
rag_startups/utils/output_formatter.py
rag_startups/utils/spinner.py
rag_startups/utils/timing.py
rag_startups-0.9.2.dist-info/licenses/LICENSE
rag_startups-0.9.2.dist-info/METADATA
rag_startups-0.9.2.dist-info/WHEEL
rag_startups-0.9.2.dist-info/entry_points.txt
rag_startups-0.9.2.dist-info/top_level.txt
rag_startups-0.9.2.dist-info/RECORD
