Metadata-Version: 2.4
Name: rag_startups
Version: 0.9.2
Summary: Generate startup ideas grounded in real YC data using Retrieval-Augmented Generation (RAG).
Home-page: https://github.com/valginer0/rag_startups
Author: Val Giner
Author-email: Val Giner <valginer0@gmail.com>
Project-URL: Homepage, https://github.com/valginer0/rag_startups
Project-URL: Repository, https://github.com/valginer0/rag_startups
Keywords: rag,ai,startup,langchain
Classifier: Programming Language :: Python :: 3
Classifier: License :: OSI Approved :: MIT License
Classifier: Operating System :: OS Independent
Requires-Python: >=3.8
License-File: LICENSE
Requires-Dist: langchain>=0.1.0
Requires-Dist: langchain-community>=0.0.1
Requires-Dist: pandas>=2.0.0
Requires-Dist: sentence-transformers>=2.2.2
Requires-Dist: transformers>=4.30.0
Requires-Dist: langchain-chroma>=0.1.0
Requires-Dist: langsmith>=0.0.30
Requires-Dist: python-dotenv>=1.0.0
Requires-Dist: backoff>=2.2.1
Requires-Dist: chromadb>=0.4.0
Requires-Dist: wbdata>=0.3.0
Requires-Dist: huggingface-hub>=0.23.0
Requires-Dist: requests>=2.31.0
Requires-Dist: redis>=5.0.1
Requires-Dist: cachetools>=5.3.2
Requires-Dist: fakeredis>=2.20.0
Requires-Dist: spacy>=3.7.2
Provides-Extra: dev
Requires-Dist: pytest>=7.0.0; extra == "dev"
Requires-Dist: pytest-cov>=4.1.0; extra == "dev"
Requires-Dist: pytest-benchmark>=4.0.0; extra == "dev"
Requires-Dist: black==24.2.0; extra == "dev"
Requires-Dist: flake8>=6.0.0; extra == "dev"
Requires-Dist: isort>=5.13.2; extra == "dev"
Requires-Dist: mypy>=1.0.0; extra == "dev"
Requires-Dist: pre-commit>=3.5.0; extra == "dev"
Provides-Extra: test
Requires-Dist: pytest>=7.0.0; extra == "test"
Requires-Dist: pytest-cov>=4.1.0; extra == "test"
Requires-Dist: pytest-benchmark>=4.0.0; extra == "test"
Provides-Extra: docs
Requires-Dist: mkdocs>=1.5.0; extra == "docs"
Requires-Dist: mkdocs-material>=9.5.0; extra == "docs"
Requires-Dist: mkdocstrings[python]>=0.24.0; extra == "docs"
Requires-Dist: mkdocs-gen-files>=0.5.0; extra == "docs"
Requires-Dist: mkdocs-literate-nav>=0.6.0; extra == "docs"
Requires-Dist: mkdocs-include-markdown-plugin>=4.0.0; extra == "docs"
Provides-Extra: publish
Requires-Dist: build>=1.0.0; extra == "publish"
Requires-Dist: twine>=4.0.0; extra == "publish"
Dynamic: author
Dynamic: home-page
Dynamic: license-file
Dynamic: requires-python
